gpgnotes/__init__.py
gpgnotes/cli.py
gpgnotes/config.py
gpgnotes/daily.py
gpgnotes/encryption.py
gpgnotes/enhance.py
gpgnotes/exporter.py
gpgnotes/history.py
gpgnotes/importer.py
gpgnotes/index.py
gpgnotes/llm.py
gpgnotes/note.py
gpgnotes/storage.py
gpgnotes/sync.py
gpgnotes/tagging.py
gpgnotes/templates.py
gpgnotes/todos.py
gpgnotes/tui/__init__.py
gpgnotes/tui/app.py
gpgnotes/tui/dialogs/__init__.py
gpgnotes/tui/dialogs/confirm.py
gpgnotes/tui/dialogs/new_note.py
gpgnotes/tui/screens/__init__.py
gpgnotes/tui/screens/help.py
gpgnotes/tui/screens/search.py
gpgnotes/tui/styles/__init__.py
gpgnotes/tui/styles/default.tcss
gpgnotes/tui/widgets/__init__.py
gpgnotes/tui/widgets/folders.py
gpgnotes/tui/widgets/notes_list.py
gpgnotes/tui/widgets/preview.py
gpgnotes/tui/widgets/tags.py
gpgnotes-0.4.2.dist-info/licenses/LICENSE
gpgnotes-0.4.2.dist-info/METADATA
gpgnotes-0.4.2.dist-info/WHEEL
gpgnotes-0.4.2.dist-info/entry_points.txt
gpgnotes-0.4.2.dist-info/top_level.txt
gpgnotes-0.4.2.dist-info/RECORD
