Metadata-Version: 2.4
Name: gpgnotes
Version: 0.4.2
Summary: GPGNotes - A CLI note-taking tool with GPG encryption, tagging, and Git sync
Author-email: "Oscar Valenzuela B." <oscar.valenzuela.b@gmail.com>
License: Apache-2.0
Project-URL: Homepage, https://github.com/oscarvalenzuelab/GPGNotes
Project-URL: Repository, https://github.com/oscarvalenzuelab/GPGNotes
Project-URL: Bug Tracker, https://github.com/oscarvalenzuelab/GPGNotes/issues
Keywords: notes,cli,markdown,encryption,gpg,git,tagging,search
Classifier: Development Status :: 3 - Alpha
Classifier: Intended Audience :: Developers
Classifier: Intended Audience :: End Users/Desktop
Classifier: License :: OSI Approved :: Apache Software License
Classifier: Programming Language :: Python :: 3
Classifier: Programming Language :: Python :: 3.11
Classifier: Programming Language :: Python :: 3.12
Classifier: Programming Language :: Python :: 3.13
Classifier: Topic :: Office/Business
Classifier: Topic :: Text Processing :: Markup :: Markdown
Classifier: Environment :: Console
Requires-Python: >=3.11
License-File: LICENSE
Requires-Dist: click>=8.1.0
Requires-Dist: python-frontmatter>=1.0.0
Requires-Dist: gitpython>=3.1.0
Requires-Dist: python-gnupg>=0.5.0
Requires-Dist: prompt-toolkit>=3.0.0
Requires-Dist: rich>=13.0.0
Requires-Dist: pyyaml>=6.0.0
Requires-Dist: python-slugify>=8.0.0
Requires-Dist: scikit-learn>=1.0.0
Provides-Extra: dev
Requires-Dist: pytest>=7.0.0; extra == "dev"
Requires-Dist: pytest-cov>=4.0.0; extra == "dev"
Requires-Dist: ruff>=0.1.0; extra == "dev"
Requires-Dist: mypy>=1.0.0; extra == "dev"
Provides-Extra: llm
Requires-Dist: openai>=1.0.0; extra == "llm"
Requires-Dist: anthropic>=0.18.0; extra == "llm"
Requires-Dist: ollama>=0.1.0; extra == "llm"
Provides-Extra: import
Requires-Dist: python-docx>=1.0.0; extra == "import"
Requires-Dist: pypdf>=4.0.0; extra == "import"
Requires-Dist: striprtf>=0.0.26; extra == "import"
Provides-Extra: tui
Requires-Dist: textual>=0.89.0; extra == "tui"
Dynamic: license-file
